{
    "error": false,
    "code": 0,
    "detail": "",
    "data": {
        "school_name": "七星大学",
        "shops": [
            {
                "shop_id": "54",
                "shop_header": "http://hyimage.uulian.com/uuhui/20160309/ee14757c674287675883dcb1bac44097.jpg",
                "type": "1",
                "shop_name": "七大自营百货",
                "base_price": "0.01",
                "notice": "神马鬼东西都有，满五减二大促销",
                "start_time": "09:00",
                "end_time": "23:00",
                "distribution": "1",
                "range": "厦门市",
                "paytype": "1",
                "overpay": "1",
                "admin_mobile": "15900000000",
                "admin_name": "",
                "chat_admin_id": "admin103",
                "admin_qq": "23232323",
                "buycount": "800",
                "goods_count": "16",
                "is_resting": false
            }
        ]
    }
}